aaaawslogger/__init__.py
aaaawslogger/aws_logger.py
aaaawslogger/aws_logger_constants.py
aaaawslogger/awslogger.py
aaaawslogger/splunk.py
aceagentlogger/__init__.py
aceagentlogger/aws_logger.py
aceagentlogger/aws_logger_constants.py
aceagentlogger/splunk.py
aws_logger/__init__.py
aws_logger/aws_logger.py
aws_logger_project/__init__.py
aws_logger_project/aws_logger.py
build/lib/aaaawslogger/__init__.py
build/lib/aaaawslogger/aws_logger.py
build/lib/aaaawslogger/aws_logger_constants.py
build/lib/aaaawslogger/awslogger.py
build/lib/aaaawslogger/splunk.py
build/lib/aws_logger/__init__.py
build/lib/aws_logger/aws_logger.py
build/lib/aws_logger_project/__init__.py
build/lib/aws_logger_project/aws_logger.py
build/lib/build/lib/aaaawslogger/__init__.py
build/lib/build/lib/aaaawslogger/aws_logger.py
build/lib/build/lib/aaaawslogger/aws_logger_constants.py
build/lib/build/lib/aaaawslogger/awslogger.py
build/lib/build/lib/aaaawslogger/splunk.py
build/lib/build/lib/aws_logger/__init__.py
build/lib/build/lib/aws_logger/aws_logger.py
build/lib/build/lib/aws_logger_project/__init__.py
build/lib/build/lib/aws_logger_project/aws_logger.py
build/lib/build/lib/build/lib/aaaawslogger/__init__.py
build/lib/build/lib/build/lib/aaaawslogger/aws_logger.py
build/lib/build/lib/build/lib/aaaawslogger/aws_logger_constants.py
build/lib/build/lib/build/lib/aaaawslogger/awslogger.py
build/lib/build/lib/build/lib/aaaawslogger/splunk.py
build/lib/build/lib/build/lib/aws_logger/__init__.py
build/lib/build/lib/build/lib/aws_logger/aws_logger.py
build/lib/build/lib/build/lib/aws_logger_project/__init__.py
build/lib/build/lib/build/lib/aws_logger_project/aws_logger.py
build/lib/build/lib/build/lib/build/lib/aaaawslogger/__init__.py
build/lib/build/lib/build/lib/build/lib/aaaawslogger/aws_logger.py
build/lib/build/lib/build/lib/build/lib/aaaawslogger/aws_logger_constants.py
build/lib/build/lib/build/lib/build/lib/aaaawslogger/awslogger.py
build/lib/build/lib/build/lib/build/lib/aaaawslogger/splunk.py
aceagentlogger-0.0.1.dist-info/METADATA
aceagentlogger-0.0.1.dist-info/WHEEL
aceagentlogger-0.0.1.dist-info/top_level.txt
aceagentlogger-0.0.1.dist-info/RECORD
