Metadata-Version: 2.1
Name: aceagentlogger
Version: 0.0.1
Summary: Logger
Author: ace
Author-email: kardaras.george@clublabs.com
Requires-Dist: boto3
